xzt_py_pkg/__init__.py
xzt_py_pkg/main.py
xzt_py_pkg/pkg_hello.py
xzt_py_pkg-0.0.1.dist-info/METADATA
xzt_py_pkg-0.0.1.dist-info/WHEEL
xzt_py_pkg-0.0.1.dist-info/top_level.txt
xzt_py_pkg-0.0.1.dist-info/RECORD
