Metadata-Version: 2.1
Name: xzt-py-pkg
Version: 0.0.1
Summary: easily test for create python pkg 
Author: xzt
Author-email: yybackbone@163.com
